lossy_image/__init__.py
lossy_image/compression.py
lossy_image/evaluation.py
lossy_image/result.py
lossy_image/algorithm/__init__.py
lossy_image/algorithm/bpg.py
lossy_image/algorithm/jpeg.py
lossy_image/algorithm/jpeg2k.py
lossy_image/algorithm/webp.py
lossy_image/metric/__init__.py
lossy_image/metric/fsim.py
lossy_image/metric/psnr.py
lossy_image/metric/size_ratio.py
lossy_image/metric/ssim.py
lossy_image-0.1.1.dist-info/METADATA
lossy_image-0.1.1.dist-info/WHEEL
lossy_image-0.1.1.dist-info/entry_points.txt
lossy_image-0.1.1.dist-info/RECORD
