Metadata-Version: 2.4
Name: lossy-image
Version: 0.1.1
Summary: A framework for performing lossy image compression using various algorithms and evaluating the compression quality with multiple metrics
Author-email: Illia Kalchenko <kalchenko.illia@gmail.com>
Requires-Python: >=3.11
Requires-Dist: pillow>=11.0.0
Requires-Dist: piq>=0.8.0
Requires-Dist: scikit-image>=0.25.0
